reticulatus/__init__.py
reticulatus/reticulatus.py
reticulatus-0.1.0.dist-info/LICENSE
reticulatus-0.1.0.dist-info/METADATA
reticulatus-0.1.0.dist-info/WHEEL
reticulatus-0.1.0.dist-info/top_level.txt
reticulatus-0.1.0.dist-info/RECORD
