Metadata-Version: 2.1
Name: reticulatus
Version: 0.1.0
Summary: Codex Reticulatus a collection of Python recipes that can help you avoid starvatinon while in the wild.
Home-page: https://github.com/ssbarnea/reticulatus
Author: Sorin Sbarnea
Author-email: sorin.sbarnea@gmail.com
License: BSD license
Keywords: reticulatus
Platform: UNKNOWN
Classifier: Development Status :: 2 - Pre-Alpha
Classifier: Intended Audience :: Developers
Classifier: License :: OSI Approved :: BSD License
Classifier: Natural Language :: English
Classifier: Programming Language :: Python :: 2
Classifier: Programming Language :: Python :: 2.7
Classifier: Programming Language :: Python :: 3
Classifier: Programming Language :: Python :: 3.4
Classifier: Programming Language :: Python :: 3.5
Classifier: Programming Language :: Python :: 3.6
Classifier: Programming Language :: Python :: 3.7
